invenio_notifications/__init__.py
invenio_notifications/config.py
invenio_notifications/errors.py
invenio_notifications/ext.py
invenio_notifications/manager.py
invenio_notifications/models.py
invenio_notifications/proxies.py
invenio_notifications/registry.py
invenio_notifications/tasks.py
invenio_notifications/views.py
invenio_notifications/backends/__init__.py
invenio_notifications/backends/base.py
invenio_notifications/backends/email.py
invenio_notifications/backends/utils/__init__.py
invenio_notifications/backends/utils/loaders.py
invenio_notifications/services/__init__.py
invenio_notifications/services/builders.py
invenio_notifications/services/filters.py
invenio_notifications/services/generators.py
invenio_notifications/services/uow.py
invenio_notifications/translations/.gitkeep
invenio_notifications/translations/messages.pot
invenio_notifications/translations/ar/LC_MESSAGES/messages.mo
invenio_notifications/translations/ar/LC_MESSAGES/messages.po
invenio_notifications/translations/bg/LC_MESSAGES/messages.mo
invenio_notifications/translations/bg/LC_MESSAGES/messages.po
invenio_notifications/translations/ca/LC_MESSAGES/messages.mo
invenio_notifications/translations/ca/LC_MESSAGES/messages.po
invenio_notifications/translations/cs/LC_MESSAGES/messages.mo
invenio_notifications/translations/cs/LC_MESSAGES/messages.po
invenio_notifications/translations/da/LC_MESSAGES/messages.mo
invenio_notifications/translations/da/LC_MESSAGES/messages.po
invenio_notifications/translations/de/LC_MESSAGES/messages.mo
invenio_notifications/translations/de/LC_MESSAGES/messages.po
invenio_notifications/translations/el/LC_MESSAGES/messages.mo
invenio_notifications/translations/el/LC_MESSAGES/messages.po
invenio_notifications/translations/en/LC_MESSAGES/messages.mo
invenio_notifications/translations/en/LC_MESSAGES/messages.po
invenio_notifications/translations/es/LC_MESSAGES/messages.mo
invenio_notifications/translations/es/LC_MESSAGES/messages.po
invenio_notifications-1.2.3.dist-info/licenses/AUTHORS.rst
invenio_notifications-1.2.3.dist-info/licenses/LICENSE
invenio_notifications-1.2.3.dist-info/METADATA
invenio_notifications-1.2.3.dist-info/WHEEL
invenio_notifications-1.2.3.dist-info/entry_points.txt
invenio_notifications-1.2.3.dist-info/top_level.txt
invenio_notifications-1.2.3.dist-info/RECORD
