Metadata-Version: 2.4
Name: invenio-notifications
Version: 1.2.3
Summary: "Invenio module for notifications support."
Home-page: https://github.com/inveniosoftware/invenio-notifications
Author: CERN
Author-email: info@inveniosoftware.org
License: MIT
Keywords: invenio TODO
Platform: any
Classifier: Development Status :: 1 - Planning
Requires-Python: >=3.7
License-File: LICENSE
License-File: AUTHORS.rst
Requires-Dist: invenio-base<3.0.0,>=2.3.0
Requires-Dist: invenio-i18n<4.0.0,>=3.0.0
Provides-Extra: tests
Requires-Dist: invenio-app<3.0.0,>=2.0.0; extra == "tests"
Requires-Dist: invenio-celery<3.0.0,>=2.0.0; extra == "tests"
Requires-Dist: invenio-mail<3.0.0,>=2.0.0; extra == "tests"
Requires-Dist: invenio-records-resources<8.0.0,>=7.0.0; extra == "tests"
Requires-Dist: pytest-invenio<4.0.0,>=3.0.0; extra == "tests"
Requires-Dist: pytest-black-ng>=0.4.0; extra == "tests"
Requires-Dist: sphinx>=4.5.0; extra == "tests"
Provides-Extra: elasticsearch7
Requires-Dist: invenio-search[elasticsearch7]<4.0.0,>=3.0.0; extra == "elasticsearch7"
Provides-Extra: opensearch2
Requires-Dist: invenio-search[opensearch2]<4.0.0,>=3.0.0; extra == "opensearch2"
Dynamic: license-file
